ax3_OTP_Auth/__init__.py
ax3_OTP_Auth/apps.py
ax3_OTP_Auth/backends.py
ax3_OTP_Auth/context_processors.py
ax3_OTP_Auth/data.py
ax3_OTP_Auth/forms.py
ax3_OTP_Auth/hotp.py
ax3_OTP_Auth/settings.py
ax3_OTP_Auth/urls.py
ax3_OTP_Auth/views.py
ax3_OTP_Auth/static/otp_auth/css/normalize.css
ax3_OTP_Auth/static/otp_auth/css/styles.css
ax3_OTP_Auth/static/otp_auth/css/styles.css.map
ax3_OTP_Auth/static/otp_auth/fonts/proxima-nova-bold.woff
ax3_OTP_Auth/static/otp_auth/fonts/proxima-nova-bold.woff2
ax3_OTP_Auth/static/otp_auth/fonts/proxima-nova-regular.woff
ax3_OTP_Auth/static/otp_auth/fonts/proxima-nova-regular.woff2
ax3_OTP_Auth/static/otp_auth/img/axiacore-logo.png
ax3_OTP_Auth/static/otp_auth/sass/_buttons.sass
ax3_OTP_Auth/static/otp_auth/sass/_general.sass
ax3_OTP_Auth/static/otp_auth/sass/_inputs.sass
ax3_OTP_Auth/static/otp_auth/sass/_typography.sass
ax3_OTP_Auth/static/otp_auth/sass/_variables.sass
ax3_OTP_Auth/static/otp_auth/sass/styles.sass
ax3_OTP_Auth/templates/otp_auth/base.html
ax3_OTP_Auth/templates/otp_auth/done.html
ax3_OTP_Auth/templates/otp_auth/start.html
ax3_OTP_Auth/templates/otp_auth/verify.html
ax3_OTP_Auth/templates/svg/_otp-success.html
AX3_OTP_Auth-1.0.5.dist-info/LICENSE
AX3_OTP_Auth-1.0.5.dist-info/METADATA
AX3_OTP_Auth-1.0.5.dist-info/WHEEL
AX3_OTP_Auth-1.0.5.dist-info/top_level.txt
AX3_OTP_Auth-1.0.5.dist-info/RECORD
