Metadata-Version: 2.1
Name: AX3-OTP-Auth
Version: 1.0.5
Summary: AX3 OTP Auth is a very simple Django library for generating and verifying one-time passwords using HTOP guidelines.
Home-page: https://github.com/Axiacore/ax3-OTP-Auth
Author: Axiacore
Author-email: info@axiacore.com
License: UNKNOWN
Platform: UNKNOWN
Classifier: Environment :: Web Environment
Classifier: Framework :: Django
Classifier: Framework :: Django :: 2.2
Classifier: Intended Audience :: Developers
Classifier: License :: OSI Approved :: MIT License
Classifier: Operating System :: OS Independent
Classifier: Programming Language :: Python :: 3.6
Classifier: Topic :: Internet :: WWW/HTTP
Classifier: Topic :: Internet :: WWW/HTTP :: Dynamic Content
Requires-Dist: boto3 (>=1.9.244)
Requires-Dist: django (>=2.2.0)
Requires-Dist: pyotp (>=2.3.0)
